Metadata-Version: 1.1
Name: djubby
Version: 0.1.7
Summary: A Linked Data frontend for SPARQL endpoints for Django
Home-page: http://djubby.googlecode.com/
Author: Sergio Fernández
Author-email: sergio@wikier.org
License: GNU Library or Lesser General Public License (LGPL) v3
Download-URL: http://code.google.com/p/djubby/downloads/list
Keywords: python django rdf sparql linkeddata
Platform: any
Classifier: Development Status :: 4 - Beta 
Classifier: Intended Audience :: Developers
Classifier: License :: OSI Approved :: GNU Library or Lesser General Public License (LGPL)
Classifier: Operating System :: OS Independent
Classifier: Programming Language :: Python :: 2.6
Requires: rdflib
Requires: SPARQLWrapper
Requires: django
Requires: mimeparse
